rubikai/__init__.py
rubikai/_openai_scripts.py
rubikai/api_requestor.py
rubikai/cli.py
rubikai/embeddings_utils.py
rubikai/error.py
rubikai/object_classes.py
rubikai/py.typed
rubikai/rubikai_object.py
rubikai/rubikai_response.py
rubikai/upload_progress.py
rubikai/util.py
rubikai/validators.py
rubikai/version.py
rubikai/wandb_logger.py
rubikai/api_resources/__init__.py
rubikai/api_resources/audio.py
rubikai/api_resources/brainos_completion.py
rubikai/api_resources/chat_completion.py
rubikai/api_resources/completion.py
rubikai/api_resources/customer.py
rubikai/api_resources/deployment.py
rubikai/api_resources/edit.py
rubikai/api_resources/embedding.py
rubikai/api_resources/engine.py
rubikai/api_resources/error_object.py
rubikai/api_resources/file.py
rubikai/api_resources/fine_tune.py
rubikai/api_resources/fine_tuning.py
rubikai/api_resources/image.py
rubikai/api_resources/model.py
rubikai/api_resources/moderation.py
rubikai/api_resources/abstract/__init__.py
rubikai/api_resources/abstract/api_resource.py
rubikai/api_resources/abstract/createable_api_resource.py
rubikai/api_resources/abstract/deletable_api_resource.py
rubikai/api_resources/abstract/engine_api_resource.py
rubikai/api_resources/abstract/listable_api_resource.py
rubikai/api_resources/abstract/nested_resource_class_methods.py
rubikai/api_resources/abstract/paginatable_api_resource.py
rubikai/api_resources/abstract/updateable_api_resource.py
rubikai/api_resources/experimental/__init__.py
rubikai/api_resources/experimental/completion_config.py
rubikai/datalib/__init__.py
rubikai/datalib/common.py
rubikai/datalib/numpy_helper.py
rubikai/datalib/pandas_helper.py
rubikai/tests/__init__.py
rubikai/tests/test_api_requestor.py
rubikai/tests/test_endpoints.py
rubikai/tests/test_exceptions.py
rubikai/tests/test_file_cli.py
rubikai/tests/test_long_examples_validator.py
rubikai/tests/test_url_composition.py
rubikai/tests/test_util.py
rubikai/tests/asyncio/__init__.py
rubikai/tests/asyncio/test_endpoints.py
yjqtest001-0.0.2.dist-info/LICENSE
yjqtest001-0.0.2.dist-info/METADATA
yjqtest001-0.0.2.dist-info/WHEEL
yjqtest001-0.0.2.dist-info/top_level.txt
yjqtest001-0.0.2.dist-info/RECORD
