Metadata-Version: 2.1
Name: yjqtest001
Version: 0.0.2
Summary: A small example package
Author-email: yaojianqu <game781120@126.com>
Project-URL: Homepage, https://github.com/yaojianqu/py-rubikai-sdk
Project-URL: Issues, https://github.com/yaojianqu/py-rubikai-sdk/issues
Classifier: Programming Language :: Python :: 3
Classifier: License :: OSI Approved :: MIT License
Classifier: Operating System :: OS Independent
Requires-Python: >=3.8
License-File: LICENSE
